guimakerp/__init__.py
GUIMakerP-1.0.1.dist-info/LICENSE.txt
GUIMakerP-1.0.1.dist-info/METADATA
GUIMakerP-1.0.1.dist-info/WHEEL
GUIMakerP-1.0.1.dist-info/top_level.txt
GUIMakerP-1.0.1.dist-info/RECORD
