Metadata-Version: 2.1
Name: GUIMakerP
Version: 1.0.1
Summary: A libaray for making simple GUI's
Home-page: UNKNOWN
Author: its_me
Author-email: rycepie3909@gmail.com
License: MIT
Keywords: guimaker
Platform: UNKNOWN
Classifier: Development Status :: 5 - Production/Stable
Classifier: Intended Audience :: Education
Classifier: Operating System :: Microsoft :: Windows :: Windows 10
Classifier: License :: OSI Approved :: MIT License
Classifier: Programming Language :: Python :: 3
